setup.py
Empire_Agent.egg-info/SOURCES.txt
empire_agent/__init__.py
empire_agent/config.py
empire_agent/daemon.py
empire_agent/design.py
empire_agent/logger.py
empire_agent/task.py
empire_agent.egg-info/PKG-INFO
empire_agent.egg-info/SOURCES.txt
empire_agent.egg-info/dependency_links.txt
empire_agent.egg-info/not-zip-safe
empire_agent.egg-info/top_level.txt