Metadata-Version: 1.0
Name: Empire-Agent
Version: 0.0.3
Summary: Empire Agent
Home-page: http://github.com/wenxer/empire-agent
Author: Shown Tien
Author-email: hightian@gmail.com
License: MIT
Platform: UNKNOWN
